usageaccountant/__init__.py
usageaccountant/accumulator.py
usageaccountant/py.typed
sentry_usage_accountant-0.0.11.dist-info/METADATA
sentry_usage_accountant-0.0.11.dist-info/WHEEL
sentry_usage_accountant-0.0.11.dist-info/top_level.txt
sentry_usage_accountant-0.0.11.dist-info/RECORD
