Metadata-Version: 2.1
Name: sentry-usage-accountant
Version: 0.0.11
Summary: A library to account for shared resource usage
Classifier: Programming Language :: Python :: 3
Classifier: Operating System :: OS Independent
Requires-Python: >=3.8
Requires-Dist: sentry-arroyo >=2.14.5
